autora/serializer/__init__.py
autora/serializer/_yaml.py
autora/workflow/__main__.py
autora_workflow-0.6.0.dist-info/LICENSE
autora_workflow-0.6.0.dist-info/METADATA
autora_workflow-0.6.0.dist-info/WHEEL
autora_workflow-0.6.0.dist-info/top_level.txt
autora_workflow-0.6.0.dist-info/RECORD
