Metadata-Version: 2.1
Name: autora-workflow
Version: 0.6.0
Summary: Workflow tools for the Autonomous Research Assistant (AutoRA) package.
Author-email: John Gerrard Holland <john_holland1@brown.edu>
License: MIT License
Project-URL: homepage, http://www.empiricalresearch.ai/
Project-URL: repository, https://github.com/AutoResearch/autora-workflow
Project-URL: documentation, https://hollandjg.github.io/autora-workflow/
License-File: LICENSE
Requires-Dist: autora-core <4.1.0,>=4.0.0
Requires-Dist: typer[all]
Provides-Extra: cylc
Requires-Dist: cylc-flow ; extra == 'cylc'
Requires-Dist: cylc-uiserver ; extra == 'cylc'
Provides-Extra: dev
Requires-Dist: autora-core[dev] <4.1.0,>=4.0.0 ; extra == 'dev'
Requires-Dist: autora-workflow[docs] ; extra == 'dev'
Requires-Dist: autora-workflow[test] ; extra == 'dev'
Provides-Extra: docs
Requires-Dist: autora-core[docs] <4.1.0,>=4.0.0 ; extra == 'docs'
Requires-Dist: scikit-learn ; extra == 'docs'
Requires-Dist: matplotlib ; extra == 'docs'
Requires-Dist: pandas ; extra == 'docs'
Provides-Extra: serializers
Requires-Dist: dill ; extra == 'serializers'
Requires-Dist: pyyaml ; extra == 'serializers'
Provides-Extra: test
Requires-Dist: autora-core[test] <4.1.0,>=4.0.0 ; extra == 'test'
Requires-Dist: autora-workflow[serializers] ; extra == 'test'
Requires-Dist: hypothesis ; extra == 'test'
Requires-Dist: scikit-learn ; extra == 'test'
Requires-Dist: pandas ; extra == 'test'
